extraction_methods/__init__.py
extraction_methods/core/__init__.py
extraction_methods/core/extraction_method.py
extraction_methods/core/types.py
extraction_methods/plugins/__init__.py
extraction_methods/plugins/assets/__init__.py
extraction_methods/plugins/assets/assets.py
extraction_methods/plugins/assets/backends/__init__.py
extraction_methods/plugins/assets/backends/elasticsearch.py
extraction_methods/plugins/assets/backends/intake_esm.py
extraction_methods/plugins/assets/backends/regex.py
extraction_methods/plugins/bbox.py
extraction_methods/plugins/ceda_observation.py
extraction_methods/plugins/ceda_vocabulary.py
extraction_methods/plugins/conditional.py
extraction_methods/plugins/controlled_vocabulary.py
extraction_methods/plugins/datetime_bound_to_centroid.py
extraction_methods/plugins/default.py
extraction_methods/plugins/dict_aggregator.py
extraction_methods/plugins/elasticsearch_aggregation.py
extraction_methods/plugins/elasticsearch_search.py
extraction_methods/plugins/facet_map.py
extraction_methods/plugins/facet_prefix.py
extraction_methods/plugins/general_function.py
extraction_methods/plugins/geometry.py
extraction_methods/plugins/geometry_to_bbox.py
extraction_methods/plugins/hash.py
extraction_methods/plugins/header/__init__.py
extraction_methods/plugins/header/backends/__init__.py
extraction_methods/plugins/header/backends/cf.py
extraction_methods/plugins/header/backends/ncml.py
extraction_methods/plugins/header/backends/xarray.py
extraction_methods/plugins/header/header.py
extraction_methods/plugins/intake_esm.py
extraction_methods/plugins/iso19115.py
extraction_methods/plugins/iso_date.py
extraction_methods/plugins/json_file.py
extraction_methods/plugins/lambda.py
extraction_methods/plugins/netcdf.py
extraction_methods/plugins/open_zip.py
extraction_methods/plugins/path_parts.py
extraction_methods/plugins/regex.py
extraction_methods/plugins/regex_label.py
extraction_methods/plugins/regex_rename.py
extraction_methods/plugins/regex_type_cast.py
extraction_methods-1.1.3.dist-info/METADATA
extraction_methods-1.1.3.dist-info/WHEEL
extraction_methods-1.1.3.dist-info/entry_points.txt
extraction_methods-1.1.3.dist-info/licenses/LICENSE
extraction_methods-1.1.3.dist-info/RECORD
